{
    "cafe": [
        {
            "twitter": {
                "tweets": [
                    "manimanihaus_o0/status/1781596705340940629"
                ],
                "tags": [
                    "MaYu_ANGEL ",
                    "5월에태어난천사",
                    "5月に生まれた天使"
                ],
                "imageLinks": [
                    "GLmAwTYbEAAc1Qz",
                    "GLmAwTYaEAAY8_d"
                ]
            },
            "startDate": 11,
            "endDate": 13,
            "locate": {
                "name": "로얄마카롱",
                "address": "서울 강남구 테헤란로25길 26 3층",
                "embed": {
                    "timestamp": "1709970284788",
                    "key": "2if2j"
                },
                "naver": "IxD7eEbf"
            }
        },
        {
            "twitter": {
                "tweets": [
                    "go_gatsu_mayu/status/1784067533919928489"
                ],
                "tags": [
                    "꽃처럼_피어날_마유의_23번째_봄",
                    "Blooming_Lilac"
                ],
                "imageLinks": [
                    "GMJH9ssasAA21rM",
                    "GMJH9stbwAAT1r9"
                ]
            },
            "startDate": 11,
            "endDate": 13,
            "locate": {
                "name": "카페크레오",
                "address": "서울 강남구 봉은사로67길 28",
                "embed": {
                    "timestamp": "1711734211127",
                    "key": "2iqgh"
                },
                "naver": "xjeg9lTY"
            }
        }
    ],
    "photo": [],
    "ad": []
}